{
  "254736577324": {
    "name": "skyvien",
    "password": "yuri"
  },
  "6283180242846": {
    "name": "Bot",
    "password": "101"
  },
  "6283823976344": {
    "name": "dikzxzx4you",
    "password": "dikzxzx4you"
  },
  "6283169964415": {
    "name": "lixx",
    "password": "storelixx"
  },
  "62812261714173": {
    "name": "LUZY",
    "password": "LUZYREALL"
  },
  "6288290753586": {
    "name": "jayz",
    "password": "jayz"
  },
  "6283139470496": {
    "name": "cl",
    "password": "cl"
  },
  "6287848918046": {
    "name": "AndiEr",
    "password": "AndiScPush22"
  },
  "6283835961139": {
    "name": "wilhan",
    "password": "wilhan"
  },
  "5491166161656": {
    "name": "DREAMXZ",
    "password": "DREAMXZ123"
  },
  "6289509472682": {
    "name": "Vannxz",
    "password": "yaya123"
  }
}